{"id": 1212, "name": "HoPro 1. Klasse", "description": "alle F\u00e4cher", "school": "Kantonsschule Hohe Promenade", "subject_count": 10, "subjects": [{"name": "BG", "weight": "1/1", "counted": true}, {"name": "Mathe", "weight": "1/1", "counted": true}, {"name": "Geographie", "weight": "1/1", "counted": true}, {"name": "Biologie", "weight": "1/1", "counted": true}, {"name": "Latein", "weight": "1/1", "counted": true}, {"name": "Franz", "weight": "1/1", "counted": true}, {"name": "Deutsch", "weight": "1/1", "counted": true}, {"name": "Englisch", "weight": "1/1", "counted": true}, {"name": "Geschichte", "weight": "1/1", "counted": true}, {"name": "Musik", "weight": "1/1", "counted": true}]}