{"id": 5548, "name": "FS 1. Klasse", "description": "Fr\u00fchlingssemester 1. Klasse am Rg", "school": "R\u00e4mib\u00fchl Z\u00fcrich", "subject_count": 8, "subjects": [{"name": "Biologie\ud83c\udf3f", "weight": "1", "counted": true}, {"name": "Deutsch\ud83c\udde9\ud83c\uddea", "weight": "1", "counted": true}, {"name": "Englisch\ud83c\uddfa\ud83c\uddf8", "weight": "1", "counted": true}, {"name": "Franz \ud83c\uddeb\ud83c\uddf7", "weight": "1", "counted": true}, {"name": "Geschichte\ud83c\udffa", "weight": "1", "counted": true}, {"name": "Latein\ud83c\udf47", "weight": "1", "counted": true}, {"name": "Mathe\u2797", "weight": "1", "counted": true}, {"name": "Musik", "weight": "0.5", "counted": true}]}