{"id": 4079, "name": "Troisi\u00e8me ann\u00e9e coll\u00e8ge (mod\u00e8le de note)", "description": "Fait pour le programme de troisi\u00e8me ann\u00e9e", "school": "Coll\u00e8ge du Sud", "subject_count": 10, "subjects": [{"name": "Allemand", "weight": "1", "counted": true}, {"name": "Anglais", "weight": "1", "counted": true}, {"name": "Fran\u00e7ais", "weight": "1", "counted": true}, {"name": "Histoire", "weight": "1", "counted": true}, {"name": "Latin", "weight": "1", "counted": true}, {"name": "Maths", "weight": "1", "counted": true}, {"name": "Musique", "weight": "1", "counted": true}, {"name": "OC philosophie", "weight": "1", "counted": true}, {"name": "Philosophie", "weight": "1", "counted": true}, {"name": "Physique", "weight": "1", "counted": true}]}