{"id": 5478, "name": "5G2 2", "description": "2.Semester", "school": "Academia Engiadina", "subject_count": 12, "subjects": [{"name": "Bildnerisches Gestalten", "weight": "1", "counted": true}, {"name": "Biologie", "weight": "1", "counted": true}, {"name": "Chemie", "weight": "1", "counted": true}, {"name": "Deutsch", "weight": "1", "counted": true}, {"name": "Englisch", "weight": "1", "counted": true}, {"name": "Geographie", "weight": "1", "counted": true}, {"name": "Geographie EF", "weight": "1", "counted": true}, {"name": "History", "weight": "1", "counted": true}, {"name": "Italienisch", "weight": "1", "counted": true}, {"name": "Mathematik", "weight": "1", "counted": true}, {"name": "Turnen", "weight": "1", "counted": true}, {"name": "Wirtschaft und Recht", "weight": "1", "counted": true}]}