{"id": 4140, "name": "Automobiltechnik BFH", "description": "Semster 1", "school": "Berner Fachhochschule", "subject_count": 9, "subjects": [{"name": "Analysis (50%)", "weight": "1", "counted": true}, {"name": "Chemie (50%)", "weight": "1", "counted": true}, {"name": "Englisch (50%)", "weight": "1", "counted": true}, {"name": "Franz\u00f6sisch (50%)", "weight": "1", "counted": true}, {"name": "Informatik (60%)", "weight": "1", "counted": true}, {"name": "Lineare Algebra / Geometrie 1 (50%)", "weight": "1", "counted": true}, {"name": "Netzwerke / Felder (50%)", "weight": "1", "counted": true}, {"name": "Physik (50%)", "weight": "1", "counted": true}, {"name": "Projektmanagement und Organisation (50%)", "weight": "1", "counted": true}]}