{"id": 3982, "name": "3\u00e8me", "description": "OC: Informatique", "school": "Coll\u00e8ge Saint-Michel", "subject_count": 10, "subjects": [{"name": "Allemand", "weight": "1", "counted": true}, {"name": "Anglais", "weight": "1", "counted": true}, {"name": "Fran\u00e7ais", "weight": "1", "counted": true}, {"name": "Histoire", "weight": "1", "counted": true}, {"name": "Informatique", "weight": "1", "counted": true}, {"name": "Italien", "weight": "1", "counted": true}, {"name": "Maths", "weight": "1", "counted": true}, {"name": "Musique", "weight": "1", "counted": true}, {"name": "Philosophie", "weight": "1", "counted": true}, {"name": "Physique", "weight": "1", "counted": true}]}